krock32/__init__.py
krock32/decode.py
krock32/encode.py
krock32-0.1.1.dist-info/LICENSE
krock32-0.1.1.dist-info/METADATA
krock32-0.1.1.dist-info/WHEEL
krock32-0.1.1.dist-info/top_level.txt
krock32-0.1.1.dist-info/RECORD
