Metadata-Version: 2.1
Name: krock32
Version: 0.1.1
Summary: Base32 encoder/decoder using Crockford's alphabet
Home-page: https://github.com/DrSLDR/krock32
Author: Jonas A. Hultén
Author-email: sldr@sldr.se
License: MIT
Platform: UNKNOWN
Classifier: License :: OSI Approved :: MIT License
Classifier: Programming Language :: Python :: 3
Classifier: Programming Language :: Python :: 3.8
